Workbook

Sheet Assumptions
A1: LBO / Acquisition Financing Model -- Key Assumptions
A3: Deal Assumptions
A4: Entry Year 0 SDE (recast, from mna_valuation_engine.py) | B4: 169975.6
A5: Entry Multiple (x Entry SDE) | B5: 3
A6: Purchase Price (Enterprise Value) | B6: =B4*B5 -> 509926.8
A7: Estimated Transaction & Closing Costs | B7: 15000
A8: Total Uses | B8: =B6+B7 -> 524926.8
A10: Capital Structure (% of Total Uses)
A11: SBA 7(a) Term Loan % | B11: 0.75
A12: Seller Note % | B12: 0.15
A13: Sponsor Equity % | B13: 0.1
A14: Check (should equal 100.0%) | B14: =B11+B12+B13 -> 1
A16: Debt Terms
A17: SBA 7(a) Rate (illustrative variable) | B17: 0.115
A18: SBA 7(a) Term (years) | B18: 10
A19: Seller Note Rate | B19: 0.06
A20: Seller Note Standby Period (yrs, interest-only) | B20: 2
A21: Seller Note Total Term (years) | B21: 5
A23: Operating Assumptions
A24: Year 0 (LTM) Revenue | B24: 1400000
A25: Year 0 SDE Margin | B25: =B4/B24 -> 0.12141114
A26: Annual Revenue Growth | B26: 0.04
A27: Margin Improvement, Years 3-5 (bps/yr) | B27: 0.005
A28: Capex (% of Revenue) | B28: 0.015
A29: Incremental NWC (% of Revenue Growth $) | B29: 0.1
A31: Exit Assumptions
A32: Base Case Exit Year | B32: 5
A33: Base Case Exit Multiple (x Exit SDE) | B33: 3

Sheet Sources & Uses
A1: Sources & Uses
A3: Uses
A4: Purchase Price (Enterprise Value) | B4: =Assumptions!B6 -> 509926.8
A5: Transaction & Closing Costs | B5: =Assumptions!B7 -> 15000
A6: Total Uses | B6: =SUM(B4:B5) -> 524926.8
A8: Sources
A9: SBA 7(a) Term Loan | B9: =$B$6*Assumptions!B11 -> 393695.1
A10: Seller Note | B10: =$B$6*Assumptions!B12 -> 78739.02
A11: Sponsor Equity | B11: =$B$6*Assumptions!B13 -> 52492.68
A12: Total Sources | B12: =SUM(B9:B11) -> 524926.8
A13: Check (Sources - Uses, should be 0) | B13: =B12-B6 -> 0
A15: Underwriting Metrics
A16: Total Debt / Entry SDE | B16: =(B9+B10)/Assumptions!B4 -> 2.7794232
A17: Sponsor Equity / Total Uses | B17: =B11/B6 -> 0.1

Sheet Operating Model
A1: Operating Model
A2: Year index (helper row for lookups) | B2: 0 | C2: 1 | D2: 2 | E2: 3 | F2: 4 | G2: 5
B3: Year 0 (LTM) | C3: Year 1 | D3: Year 2 | E3: Year 3 | F3: Year 4 | G3: Year 5
A4: Revenue | B4: =Assumptions!B24 -> 1400000 | C4: =B4*(1+Assumptions!$B$26) -> 1456000 | D4: =C4*(1+Assumptions!$B$26) -> 1514240 | E4: =D4*(1+Assumptions!$B$26) -> 1574809.6 | F4: =E4*(1+Assumptions!$B$26) -> 1637802 | G4: =F4*(1+Assumptions!$B$26) -> 1703314.1
A5: Revenue Growth % | C5: =C4/B4-1 -> 0.04 | D5: =D4/C4-1 -> 0.04 | E5: =E4/D4-1 -> 0.04 | F5: =F4/E4-1 -> 0.04 | G5: =G4/F4-1 -> 0.04
A6: SDE / EBITDA Margin % | B6: =Assumptions!B25 -> 0.12141114 | C6: =B6 -> 0.12141114 | D6: =C6 -> 0.12141114 | E6: =D6+Assumptions!$B$27 -> 0.12641114 | F6: =E6+Assumptions!$B$27 -> 0.13141114 | G6: =F6+Assumptions!$B$27 -> 0.13641114
A7: SDE / EBITDA ($) | B7: =B4*B6 -> 169975.6 | C7: =C4*C6 -> 176774.62 | D7: =D4*D6 -> 183845.61 | E7: =E4*E6 -> 199073.48 | F7: =F4*F6 -> 215225.43 | G7: =G4*G6 -> 232351.02
A9: Less: Capex | C9: =-C4*Assumptions!$B$28 -> -21840 | D9: =-D4*Assumptions!$B$28 -> -22713.6 | E9: =-E4*Assumptions!$B$28 -> -23622.144 | F9: =-F4*Assumptions!$B$28 -> -24567.03 | G9: =-G4*Assumptions!$B$28 -> -25549.711
A10: Less: Incremental NWC | C10: =-(C4-B4)*Assumptions!$B$29 -> -5600 | D10: =-(D4-C4)*Assumptions!$B$29 -> -5824 | E10: =-(E4-D4)*Assumptions!$B$29 -> -6056.96 | F10: =-(F4-E4)*Assumptions!$B$29 -> -6299.2384 | G10: =-(G4-F4)*Assumptions!$B$29 -> -6551.2079
A12: Unlevered Free Cash Flow (pre-debt-service) | C12: =C7+C9+C10 -> 149334.62 | D12: =D7+D9+D10 -> 155308.01 | E12: =E7+E9+E10 -> 169394.38 | F12: =F7+F9+F10 -> 184359.16 | G12: =G7+G9+G10 -> 200250.1
A14: Note: modeled at the pre-tax, pass-through SDE level appropriate for a small-business acquisition, not a full corporate-tax LBO -- see README > Limitations.

Sheet Debt Schedule
A1: Debt Schedule
B3: At Close | C3: Year 1 | D3: Year 2 | E3: Year 3 | F3: Year 4 | G3: Year 5
A5: SBA 7(a) Term Loan
A6: Beginning Balance | B6: ='Sources & Uses'!B9 -> 393695.1 | C6: =B6 -> 393695.1 | D6: =C10 -> 370712.28 | E6: =D10 -> 345086.43 | F6: =E10 -> 316513.61 | G6: =F10 -> 284654.92
A7: Annual Debt Service (level P&I) | C7: =-PMT(Assumptions!$B$17,Assumptions!$B$18,'Sources & Uses'!$B$9) -> 68257.758 | D7: =-PMT(Assumptions!$B$17,Assumptions!$B$18,'Sources & Uses'!$B$9) -> 68257.758 | E7: =-PMT(Assumptions!$B$17,Assumptions!$B$18,'Sources & Uses'!$B$9) -> 68257.758 | F7: =-PMT(Assumptions!$B$17,Assumptions!$B$18,'Sources & Uses'!$B$9) -> 68257.758 | G7: =-PMT(Assumptions!$B$17,Assumptions!$B$18,'Sources & Uses'!$B$9) -> 68257.758
A8: Interest Expense | C8: =C6*Assumptions!$B$17 -> 45274.937 | D8: =D6*Assumptions!$B$17 -> 42631.912 | E8: =E6*Assumptions!$B$17 -> 39684.94 | F8: =F6*Assumptions!$B$17 -> 36399.066 | G8: =G6*Assumptions!$B$17 -> 32735.316
A9: Principal Payment | C9: =C7-C8 -> 22982.822 | D9: =D7-D8 -> 25625.846 | E9: =E7-E8 -> 28572.818 | F9: =F7-F8 -> 31858.693 | G9: =G7-G8 -> 35522.442
A10: Ending Balance | C10: =C6-C9 -> 370712.28 | D10: =D6-D9 -> 345086.43 | E10: =E6-E9 -> 316513.61 | F10: =F6-F9 -> 284654.92 | G10: =G6-G9 -> 249132.48
A13: Seller Note (2-yr standby, then amortizes)
A14: Beginning Balance | B14: ='Sources & Uses'!B10 -> 78739.02 | C14: =B14 -> 78739.02 | D14: =C18 -> 78739.02 | E14: =D18 -> 78739.02 | F14: =E18 -> 54006.321 | G14: =F18 -> 27789.66
A15: Interest Expense | C15: =C14*Assumptions!$B$19 -> 4724.3412 | D15: =D14*Assumptions!$B$19 -> 4724.3412 | E15: =E14*Assumptions!$B$19 -> 4724.3412 | F15: =F14*Assumptions!$B$19 -> 3240.3793 | G15: =G14*Assumptions!$B$19 -> 1667.3796
A16: Post-Standby Annual P&I (Yrs 3-5) | E16: =-PMT(Assumptions!$B$19,Assumptions!$B$21-Assumptions!$B$20,E14) -> 29457.04 | F16: =E16 -> 29457.04 | G16: =F16 -> 29457.04
A17: Principal Payment | C17: 0 | D17: 0 | E17: =E16-E15 -> 24732.699 | F17: =F16-F15 -> 26216.661 | G17: =G16-G15 -> 27789.66
A18: Ending Balance | C18: =C14-C17 -> 78739.02 | D18: =D14-D17 -> 78739.02 | E18: =E14-E17 -> 54006.321 | F18: =F14-F17 -> 27789.66 | G18: =G14-G17 -> 0
A21: Consolidated Debt Service & Coverage
A22: Total Debt Service (SBA P&I + Seller Note I+P) | C22: =C7+C15+C17 -> 72982.099 | D22: =D7+D15+D17 -> 72982.099 | E22: =E7+E15+E17 -> 97714.798 | F22: =F7+F15+F17 -> 97714.798 | G22: =G7+G15+G17 -> 97714.798
A23: SDE / EBITDA (from Operating Model) | C23: ='Operating Model'!C7 -> 176774.62 | D23: ='Operating Model'!D7 -> 183845.61 | E23: ='Operating Model'!E7 -> 199073.48 | F23: ='Operating Model'!F7 -> 215225.43 | G23: ='Operating Model'!G7 -> 232351.02
A24: DSCR (EBITDA / Total Debt Service) | C24: =C23/C22 -> 2.4221641 | D24: =D23/D22 -> 2.5190507 | E24: =E23/E22 -> 2.037291 | F24: =F23/F22 -> 2.2025879 | G24: =G23/G22 -> 2.3778488
A25: Free Cash Flow after Debt Service (to Equity) | C25: ='Operating Model'!C12-C22 -> 76352.525 | D25: ='Operating Model'!D12-D22 -> 82325.91 | E25: ='Operating Model'!E12-E22 -> 71679.579 | F25: ='Operating Model'!F12-F22 -> 86644.364 | G25: ='Operating Model'!G12-G22 -> 102535.3
A27: Total Debt Outstanding, End of Year (SBA + Seller Note) | C27: =C10+C18 -> 449451.3 | D27: =D10+D18 -> 423825.45 | E27: =E10+E18 -> 370519.94 | F27: =F10+F18 -> 312444.58 | G27: =G10+G18 -> 249132.48

Sheet Returns Analysis
A1: Returns Analysis
A3: Base Case Exit
A4: Exit Year | B4: =Assumptions!B32 -> 5
A5: Exit Multiple (x SDE) | B5: =Assumptions!B33 -> 3
A6: Exit Year SDE / EBITDA | B6: =INDEX('Operating Model'!$C$7:$G$7,MATCH($B$4,'Operating Model'!$C$2:$G$2,0)) -> 232351.02
A7: Exit Enterprise Value | B7: =B6*B5 -> 697053.05
A8: Less: Net Debt at Exit | B8: =INDEX('Debt Schedule'!$C$27:$G$27,MATCH($B$4,'Operating Model'!$C$2:$G$2,0)) -> 249132.48
A9: Exit Equity Value | B9: =B7-B8 -> 447920.57
A10: Initial Sponsor Equity | B10: ='Sources & Uses'!B11 -> 52492.68
A11: MOIC | B11: =B9/B10 -> 8.5330102
A12: IRR (single lump-sum exit, no interim distributions) | B12: =(B11)^(1/B4)-1 -> 0.53539617
A15: Sensitivity: MOIC by Exit Multiple x Exit Year
B16: Exit Multiple \ Exit Year | C16: 3 | D16: 4 | E16: 5
B17: 2.5 | C17: =(INDEX('Operating Model'!$C$7:$G$7,MATCH(C$16,'Operating Model'!$C$2:$G$2,0))*$B17-INDEX('Debt Schedule'!$C$27:$G$27,MATCH(C$16,'Operating Model'!$C$2:$G$2,0)))/'Sources & Uses'!$B$11 -> 2.4225048 | D17: =(INDEX('Operating Model'!$C$7:$G$7,MATCH(D$16,'Operating Model'!$C$2:$G$2,0))*$B17-INDEX('Debt Schedule'!$C$27:$G$27,MATCH(D$16,'Operating Model'!$C$2:$G$2,0)))/'Sources & Uses'!$B$11 -> 4.2981039 | E17: =(INDEX('Operating Model'!$C$7:$G$7,MATCH(E$16,'Operating Model'!$C$2:$G$2,0))*$B17-INDEX('Debt Schedule'!$C$27:$G$27,MATCH(E$16,'Operating Model'!$C$2:$G$2,0)))/'Sources & Uses'!$B$11 -> 6.3198348
B18: 3 | C18: =(INDEX('Operating Model'!$C$7:$G$7,MATCH(C$16,'Operating Model'!$C$2:$G$2,0))*$B18-INDEX('Debt Schedule'!$C$27:$G$27,MATCH(C$16,'Operating Model'!$C$2:$G$2,0)))/'Sources & Uses'!$B$11 -> 4.3187071 | D18: =(INDEX('Operating Model'!$C$7:$G$7,MATCH(D$16,'Operating Model'!$C$2:$G$2,0))*$B18-INDEX('Debt Schedule'!$C$27:$G$27,MATCH(D$16,'Operating Model'!$C$2:$G$2,0)))/'Sources & Uses'!$B$11 -> 6.3481558 | E18: =(INDEX('Operating Model'!$C$7:$G$7,MATCH(E$16,'Operating Model'!$C$2:$G$2,0))*$B18-INDEX('Debt Schedule'!$C$27:$G$27,MATCH(E$16,'Operating Model'!$C$2:$G$2,0)))/'Sources & Uses'!$B$11 -> 8.5330102
B19: 3.5 | C19: =(INDEX('Operating Model'!$C$7:$G$7,MATCH(C$16,'Operating Model'!$C$2:$G$2,0))*$B19-INDEX('Debt Schedule'!$C$27:$G$27,MATCH(C$16,'Operating Model'!$C$2:$G$2,0)))/'Sources & Uses'!$B$11 -> 6.2149094 | D19: =(INDEX('Operating Model'!$C$7:$G$7,MATCH(D$16,'Operating Model'!$C$2:$G$2,0))*$B19-INDEX('Debt Schedule'!$C$27:$G$27,MATCH(D$16,'Operating Model'!$C$2:$G$2,0)))/'Sources & Uses'!$B$11 -> 8.3982076 | E19: =(INDEX('Operating Model'!$C$7:$G$7,MATCH(E$16,'Operating Model'!$C$2:$G$2,0))*$B19-INDEX('Debt Schedule'!$C$27:$G$27,MATCH(E$16,'Operating Model'!$C$2:$G$2,0)))/'Sources & Uses'!$B$11 -> 10.746186
A22: Sensitivity: IRR by Exit Multiple x Exit Year
B23: Exit Multiple \ Exit Year | C23: 3 | D23: 4 | E23: 5
B24: 2.5 | C24: =(C17)^(1/C$23)-1 -> 0.34303773 | D24: =(D17)^(1/D$23)-1 -> 0.43985656 | E24: =(E17)^(1/E$23)-1 -> 0.44590961
B25: 3 | C25: =(C18)^(1/C$23)-1 -> 0.62848808 | D25: =(D18)^(1/D$23)-1 -> 0.58731052 | E25: =(E18)^(1/E$23)-1 -> 0.53539617
B26: 3.5 | C26: =(C19)^(1/C$23)-1 -> 0.83856195 | D26: =(D19)^(1/D$23)-1 -> 0.70234136 | E26: =(E19)^(1/E$23)-1 -> 0.60786976

Sheet Notes & Limitations
A1: Notes & Limitations
A3: This model works at the pre-tax, pass-through SDE level appropriate for a small-business acquisition -- it does not model corporate income tax, depreciation/amortization schedules, or deferred tax effects.
A5: No cash sweep or voluntary prepayment is modeled on the SBA loan. Real SBA 7(a) loans commonly carry prepayment penalties in years 1-3 (typically 5%/3%/1% of the prepaid amount), so a cash sweep would need to weigh that cost -- omitted here for simplicity, not because it wouldn't matter.
A7: The exit calculation assumes a single lump-sum equity distribution at exit with no interim dividends or recapitalizations -- realistic for a buy-and-hold independent-sponsor deal, less realistic for a fund that takes dividend recaps along the way.
A9: SBA loan rate, sponsor equity %, and transaction cost assumptions are illustrative Q3 2026 ballparks, not sourced from a live SBA SOP or lender term sheet -- flagged individually on the Assumptions tab, consistent with this repo's verified/unverified labeling elsewhere.
A11: DSCR covenant threshold (1.15x-1.25x cited on the Debt Schedule tab) is a general small-business lending ballpark, not a specific lender's actual covenant -- confirm with the real lender's term sheet before relying on it.
A13: This is a portfolio project. The deal, business, and dollar figures are illustrative and tie to the same anonymized scenario as mna_valuation_engine.py elsewhere in this repo -- no real business's financial data appears here.
A15: Base-case MOIC/IRR (see Returns Analysis) run well above a typical institutional LBO. That is a direct, mechanical consequence of the SBA capital structure, not an optimistic growth assumption doing the work: sponsor equity is only ~10% of total uses (the SBA's real minimum injection for a change-of-ownership loan), so the same dollar of EBITDA growth and debt paydown is divided by a much smaller equity base than a traditional 30-40%-equity deal would use. This is the standard economic argument for SBA-financed search-fund and independent-sponsor acquisitions -- small equity checks amplify returns -- and it cuts both ways: the same leverage that produces an 8x+ MOIC here would produce a proportionally larger equity wipeout if SDE declined instead of grew.
